<?xml version="1.0"?>
<users>
  <user>
    <id>1</id>
    <username>agornluta</username>
    <password>tVqdU92GL2cOUolplk3YxQ==</password>
    <salt>VCtc0P2op//LleJ6</salt>
  </user>
  <user>
    <id>2</id>
    <username>petritluta</username>
    <password>3SgGEoONLft9JT2jKiEFUQ==</password>
    <salt>B7y+2ijU+fkRoNUO</salt>
  </user>
  <user>
    <id>3</id>
    <username>rigonluta</username>
    <password>Tuyhz4dbnZvNj5AKGGWN1Q==</password>
    <salt>48piyLuVzUnZ15w6</salt>
  </user>
  <user>
    <id>4</id>
    <username>petritluta123</username>
    <password>bRafPi2Vocu5uM+KZSZzjQ==</password>
    <salt>iQ3gAVtSLf0L6BV+</salt>
  </user>
  <user>
    <id>5</id>
    <username>petrit123</username>
    <password>4DPnQTDjSgH5xELVpG9/TA==</password>
    <salt>jmjntYa6IutbZgK9</salt>
  </user>
  <user>
    <id>6</id>
    <username>petrdvorak</username>
    <password>PVvurOop5e6/QrPi/qRw2Q==</password>
    <salt>sS6CVo9eob8MnZ4V</salt>
  </user>
  <user>
    <id>7</id>
    <username>agron</username>
    <password>fak2ZEOVGFcCtfx9spLhuw==</password>
    <salt>8b/InkL3O7NQ7Mnj</salt>
  </user>
  <user>
    <id>8</id>
    <username>gony</username>
    <password>weaNv9qM/i3GhyhJsAaLPw==</password>
    <salt>opBwxZ3zYIF16+Sx</salt>
  </user>
  <user>
    <id>9</id>
    <username>petr123</username>
    <password>1wJa2uz4UqEfM2YjHdhzkQ==</password>
    <salt>LKDlE2MqiEpjx8OJ</salt>
  </user>
  <user>
    <id>10</id>
    <username>petr1265</username>
    <password>a6Z+HrKLQV0zcL6FJH9rOA==</password>
    <salt>d0ShGsgGp5gihnxL</salt>
  </user>
  <user>
    <id>11</id>
    <username>petrit12345</username>
    <password>TeMWNKfuLsaltgr9DCB0+g==</password>
    <salt>uAjj8+Wcp7AIf+zR</salt>
  </user>
  <user>
    <id>12</id>
    <username>asd213</username>
    <password>NtR6o8JMlmfHECl7MCpgMg==</password>
    <salt>OtLs/16JFazcQmmr</salt>
  </user>
  <user>
    <id>13</id>
    <username>nuredinvokrri</username>
    <password>scmhhs2I4BG+OdT7QMOvlw==</password>
    <salt>A3+az9KA1WVqPdqR</salt>
  </user>
  <user>
    <id>14</id>
    <username>samiballabani</username>
    <password>XFOAoCXBJvMtjMAEXWhIMQ==</password>
    <salt>5YZK+M2wCcKF7iyW</salt>
  </user>
  <user>
    <id>15</id>
    <username>kondukter</username>
    <password>eFekPvQC/zU3BRdPmrplLQ==</password>
    <salt>+uV3cBKrSDpp2s9l</salt>
  </user>
  <user>
    <id>16</id>
    <username>nuredini</username>
    <password>0mLtEI05QpCUMV8rg7AXoQ==</password>
    <salt>eVL9xAN//0iHeA0n</salt>
  </user>
  <user>
    <id>17</id>
    <username>testimi</username>
    <password>brN+tu/Qo+q0dTvNGzQCqw==</password>
    <salt>hMEqQlV7a8Q3B8Ec</salt>
  </user>
  <user>
    <id>18</id>
    <username>vesa</username>
    <password>oJa5IhA9dknr6u1J57Ngsg==</password>
    <salt>SwmgErSSdYMq77WJ</salt>
  </user>
</users>